[
  {
    "id": "3a552620-c26d-49b4-974a-8f65adf556b0",
    "data": [
      {
        "text": "sounds good",
        "userDefined": false
      }
    ],
    "isTemplate": false,
    "count": 0,
    "updated": 0
  },
  {
    "id": "987e8523-a8d7-4bd9-9e97-afdf811507bd",
    "data": [
      {
        "text": "of course",
        "userDefined": false
      }
    ],
    "isTemplate": false,
    "count": 0,
    "updated": 0
  },
  {
    "id": "3eeea870-3001-4a39-836d-da21b7748c5f",
    "data": [
      {
        "text": "I agree",
        "userDefined": false
      }
    ],
    "isTemplate": false,
    "count": 1,
    "updated": 0
  },
  {
    "id": "9789a30e-1d56-43ce-abbc-e1e58d8e7c94",
    "data": [
      {
        "text": "do it",
        "userDefined": false
      }
    ],
    "isTemplate": false,
    "count": 1,
    "updated": 0
  },
  {
    "id": "c0ccecdb-960f-41b2-9b2f-282ef370ff25",
    "data": [
      {
        "text": "okay",
        "userDefined": false
      }
    ],
    "isTemplate": false,
    "count": 0,
    "updated": 1505507989
  },
  {
    "id": "ebfd5a9b-a6d5-4419-a356-2d9ef477e45a",
    "data": [
      {
        "text": "exactly",
        "userDefined": false
      }
    ],
    "isTemplate": false,
    "count": 0,
    "updated": 0
  },
  {
    "id": "ae4582a9-ffab-4ac5-bd18-780e2206c35a",
    "data": [
      {
        "text": "sure",
        "userDefined": false
      }
    ],
    "isTemplate": false,
    "count": 2,
    "updated": 0
  },
  {
    "id": "fa33ccd0-b60c-42b3-89ed-f1b03f8c3b7f",
    "data": [
      {
        "text": "ok",
        "userDefined": false
      }
    ],
    "isTemplate": false,
    "count": 0,
    "updated": 1505507989
  },
  {
    "id": "3b601ab6-ec54-4253-a0b9-49bc0ffd94a4",
    "data": [
      {
        "text": "confirm",
        "userDefined": false
      }
    ],
    "isTemplate": false,
    "count": 1,
    "updated": 0
  },
  {
    "id": "b24a9dc5-da9d-47b4-89b5-e6f2a69829ff",
    "data": [
      {
        "text": "I don\u0027t mind",
        "userDefined": false
      }
    ],
    "isTemplate": false,
    "count": 0,
    "updated": 0
  },
  {
    "id": "8d71c625-5a4f-42da-8d98-ef3bc211e982",
    "data": [
      {
        "text": "that\u0027s correct",
        "userDefined": false
      }
    ],
    "isTemplate": false,
    "count": 0,
    "updated": 0
  },
  {
    "id": "b0e7a1b5-daa3-4d8b-9e9a-27a06ded4016",
    "data": [
      {
        "text": "yes",
        "userDefined": false
      }
    ],
    "isTemplate": false,
    "count": 0,
    "updated": 0
  }
]