[
  {
    "id": "0ff6d085-3ca9-4a07-b6a2-3d32d4712bb3",
    "data": [
      {
        "text": "initialize @sys.any:variable as @sys.any:value",
        "userDefined": false
      }
    ],
    "isTemplate": true,
    "count": 0,
    "updated": 0
  },
  {
    "id": "70d4ccfe-dcdb-4612-ba60-532292f8c590",
    "data": [
      {
        "text": "@sys.any:variable \u003d @sys.any:value",
        "userDefined": false
      }
    ],
    "isTemplate": true,
    "count": 0,
    "updated": 0
  },
  {
    "id": "3e8d78d1-d370-4376-b1dd-ab0b1be54d56",
    "data": [
      {
        "text": "let @sys.any:variable equal to @sys.any:value",
        "userDefined": false
      }
    ],
    "isTemplate": true,
    "count": 0,
    "updated": 0
  },
  {
    "id": "81b7d493-003d-4750-bec4-206cf2eecf3d",
    "data": [
      {
        "text": "create a variable @sys.any:variable equals to @sys.any:value",
        "userDefined": false
      }
    ],
    "isTemplate": true,
    "count": 0,
    "updated": 0
  },
  {
    "id": "9968c41b-bf91-4164-bb26-2509db056dbc",
    "data": [
      {
        "text": "assign @sys.any:variable the value @sys.any:value",
        "userDefined": false
      }
    ],
    "isTemplate": true,
    "count": 0,
    "updated": 0
  },
  {
    "id": "ffa3a352-4d44-43ec-a58f-6debb1d699fa",
    "data": [
      {
        "text": "set @sys.any:variable equal to @sys.any:value",
        "userDefined": false
      }
    ],
    "isTemplate": true,
    "count": 0,
    "updated": 0
  },
  {
    "id": "a540b16f-2858-4cf6-be46-d590fd5d5358",
    "data": [
      {
        "text": "let @sys.any:variable equal @sys.any:value",
        "userDefined": false
      }
    ],
    "isTemplate": true,
    "count": 0,
    "updated": 0
  },
  {
    "id": "bbefa6ab-67ad-4951-b82d-25fd689f58be",
    "data": [
      {
        "text": "@sys.any:variable equals @sys.any:value",
        "userDefined": false
      }
    ],
    "isTemplate": true,
    "count": 0,
    "updated": 0
  }
]