[
  {
    "id": "90180ce4-4627-4ef8-af61-e10829881834",
    "data": [
      {
        "text": "repeat @sys.number-integer:times time",
        "userDefined": false
      }
    ],
    "isTemplate": true,
    "count": 0,
    "updated": 1524279047
  },
  {
    "id": "98fcddde-28b0-4159-849a-b95756e654cd",
    "data": [
      {
        "text": "repeat @sys.number-integer:times times",
        "userDefined": false
      }
    ],
    "isTemplate": true,
    "count": 0,
    "updated": 1524279047
  },
  {
    "id": "3356e5c6-5df5-44bb-8ab4-83580bedff26",
    "data": [
      {
        "text": "repeat the following @sys.number-integer:times times",
        "userDefined": false
      }
    ],
    "isTemplate": true,
    "count": 0,
    "updated": 1524279047
  },
  {
    "id": "b16bf181-2122-40c6-b67b-0be9194c86a5",
    "data": [
      {
        "text": "repeating @sys.number-integer:times times",
        "userDefined": false
      }
    ],
    "isTemplate": true,
    "count": 0,
    "updated": 1524527539
  },
  {
    "id": "9cf776b5-9c48-4409-a983-ec7b09ded279",
    "data": [
      {
        "text": "repeat the next step @sys.number-integer:times times",
        "userDefined": false
      }
    ],
    "isTemplate": true,
    "count": 1,
    "updated": 1524279047
  }
]